BUGS.txt
CHANGES.txt
COPYING
INSTALL.txt
LICENSE.txt
MANIFEST.in
README.txt
ez_setup.py
setup.py
.hg/last-message.txt
docs/funcs.otl
docs/functions.html
docs/programming_notes.wiki
docs/syntax.txt
misc/README.core.templ
misc/README.rest.templ
misc/README.txt.templ
misc/demo.templ
misc/functions.templ
misc/html.itmpl
misc/rest.itmpl
misc/templ.vim
misc/tutorial.core.templ
misc/tutorial.css
misc/tutorial.rest.templ
misc/txtdoc.itmpl
templ/__init__.py
templ/filepos.py
templ/stack.py
templ/tbuiltin.py
templ/templ.py
templ/teval.py
templ/texceptions.py
templ/texec.py
templ/tstreams.py
templ/ttypes.py
templ/version.py
templ.egg-info/PKG-INFO
templ.egg-info/SOURCES.txt
templ.egg-info/dependency_links.txt
templ.egg-info/entry_points.txt
templ.egg-info/top_level.txt