Metadata-Version: 1.0
Name: templ
Version: 1.2.0.0
Summary: Template Processing Language.
Home-page: https://bitbucket.org/bmearns/templ/
Author: Brian Mearns
Author-email: bmearns@ieee.org
License:                     GNU AFFERO GENERAL PUBLIC LICENSE
